{
  "": {
    "colors": {
      "primary": {
        "$type": "color",
        "$value": "#3182ce"
      },
      "secondary": {
        "$type": "color",
        "$value": "#805ad5"
      }
    },
    "spacing": {
      "xs": {
        "$type": "spacing",
        "$value": "4"
      }
    }
  },
  "core": {
    "colors": {
      "primary": {
        "$type": "color",
        "$value": "#3182ce"
      },
      "secondary": {
        "$type": "color",
        "$value": "#805ad5"
      }
    },
    "spacing": {
      "xs": {
        "$type": "spacing",
        "$value": "77"
      }
    }
  },
  "$themes": [],
  "$metadata": {
    "tokenSetOrder": [
      "",
      "core"
    ]
  }
}